barkcli.py
barkcli-1.0.5.dist-info/METADATA
barkcli-1.0.5.dist-info/WHEEL
barkcli-1.0.5.dist-info/entry_points.txt
barkcli-1.0.5.dist-info/top_level.txt
barkcli-1.0.5.dist-info/RECORD
