Metadata-Version: 2.4
Name: barkcli
Version: 1.0.5
Summary: CLI tool for sending notifications to Bark
Author: FalconChen
Author-email: falcon_chen@qq.com
License: MIT
Classifier: Programming Language :: Python :: 3
Classifier: Operating System :: OS Independent
Requires-Python: >=3.6
Requires-Dist: requests
Requires-Dist: barknotificator>=0.2.0
Dynamic: author
Dynamic: author-email
Dynamic: classifier
Dynamic: description
Dynamic: description-content-type
Dynamic: license
Dynamic: requires-dist
Dynamic: requires-python
Dynamic: summary
